examples/__init__.py
examples/dcgan.py
examples/imagenet.py
examples/mnist.py
torchdp/__init__.py
torchdp/autograd_grad_sample.py
torchdp/dp_model_inspector.py
torchdp/per_sample_gradient_clip.py
torchdp/privacy_analysis.py
torchdp/privacy_engine.py
torchdp/stats.py
torchdp/supported_layers_grad_samplers.py
torchdp/utils.py
torchdp/layers/__init__.py
torchdp/layers/dp_multihead_attention.py
torchdp/test/__init__.py
torchdp/test/dp_layers_test.py
torchdp/test/dp_model_inspector_test.py
torchdp/test/layers_grad_test.py
torchdp/test/per_sample_gradient_clip_test.py
torchdp/test/privacy_engine_test.py
torchdp/test/utils_test.py
pytorch_dp-0.1b1.dist-info/LICENSE
pytorch_dp-0.1b1.dist-info/METADATA
pytorch_dp-0.1b1.dist-info/WHEEL
pytorch_dp-0.1b1.dist-info/top_level.txt
pytorch_dp-0.1b1.dist-info/RECORD
