Metadata-Version: 2.1
Name: pytorch-dp
Version: 0.1b1
Summary: Train PyTorch models with Differential Privacy
Home-page: https://github.com/facebookresearch/pytorch-dp
Author: PyTorch Team
License: Apache-2.0
Platform: UNKNOWN
Classifier: Programming Language :: Python :: 3
Classifier: Operating System :: OS Independent
Requires-Python: >=3.6
Requires-Dist: attrs (==19.3.0)
Requires-Dist: bleach (==3.1.5)
Requires-Dist: certifi (==2020.4.5.1)
Requires-Dist: chardet (==3.0.4)
Requires-Dist: docutils (==0.16)
Requires-Dist: future (==0.18.2)
Requires-Dist: idna (==2.9)
Requires-Dist: importlib-metadata (==1.6.0)
Requires-Dist: keyring (==21.2.1)
Requires-Dist: more-itertools (==8.3.0)
Requires-Dist: numpy (==1.18.4)
Requires-Dist: packaging (==20.4)
Requires-Dist: Pillow (==7.1.2)
Requires-Dist: pkginfo (==1.5.0.1)
Requires-Dist: pluggy (==0.13.1)
Requires-Dist: py (==1.8.1)
Requires-Dist: Pygments (==2.6.1)
Requires-Dist: pyparsing (==2.4.7)
Requires-Dist: pytest (==5.4.2)
Requires-Dist: readme-renderer (==26.0)
Requires-Dist: requests (==2.23.0)
Requires-Dist: requests-toolbelt (==0.9.1)
Requires-Dist: scipy (==1.4.1)
Requires-Dist: six (==1.14.0)
Requires-Dist: torch (==1.5.0)
Requires-Dist: torchvision (==0.6.0)
Requires-Dist: tqdm (==4.46.0)
Requires-Dist: twine (==3.1.1)
Requires-Dist: urllib3 (==1.25.9)
Requires-Dist: wcwidth (==0.1.9)
Requires-Dist: webencodings (==0.5.1)
Requires-Dist: zipp (==3.1.0)
